mc_generator_utils/__init__.py
mc_generator_utils/img.py
mc_generator_utils/md.py
mc_generator_utils-0.0.2.dist-info/METADATA
mc_generator_utils-0.0.2.dist-info/WHEEL
mc_generator_utils-0.0.2.dist-info/top_level.txt
mc_generator_utils-0.0.2.dist-info/RECORD
