Metadata-Version: 2.1
Name: mc-generator-utils
Version: 0.0.2
Summary: Utility functions for minecraft data and assets generation
Author-email: Julian Wandhoven <Julian.wandhoven@gamil.com>
Project-URL: Homepage, https://github.com/JulianWww/Minecraft-Generator-Utils
Project-URL: Bug Tracker, https://github.com/JulianWww/Minecraft-Generator-Utils/issues
Classifier: Programming Language :: Python :: 3
Classifier: License :: OSI Approved :: MIT License
Classifier: Operating System :: OS Independent
Requires-Python: >=3.7
